{
    "Apps": [
        {
            "IntuneAppName": "7-Zip",
            "AppPublisher": "Igor Pavlov",
            "AppSource": "Evergreen",
            "AppID": "7zip",
            "AppFolderName": "7zip",
            "AppSetupFileName": "setup_7zip.msi",
            "FilterOptions": [
                {
                    "Architecture": "x64",
                    "Type": "msi"
                }
            ]
        },
        {
            "IntuneAppName": "Notepad++",
            "AppPublisher": "Don Ho",
            "AppSource": "Evergreen",
            "AppID": "NotepadPlusPlus",
            "AppFolderName": "NotepadPlusPlus",
            "AppSetupFileName": "setup_notepad.exe",
            "FilterOptions": [
                {
                    "Architecture": "x64",
                    "Type": "exe"
                }
            ]
        },
        {
            "IntuneAppName": "TreeSize Free",
            "AppPublisher": "Jam Software",
            "AppSource": "Winget",
            "AppID": "JAMSoftware.TreeSize.Free",
            "AppFolderName": "TreeSize Free",
            "AppSetupFileName": "TreeSizeFreeSetup.exe"
        },
        {
            "IntuneAppName": "Steam",
            "AppPublisher": "Valve",
            "AppSource": "Winget",
            "AppID": "Valve.Steam",
            "AppFolderName": "Steam",
            "AppSetupFileName": "SteamSetup.exe"
        },
    
        
    ]
}